src/__init__.py
src/main.py
src/pliers.py
CBZpliers-0.2.0.dist-info/LICENSE
CBZpliers-0.2.0.dist-info/METADATA
CBZpliers-0.2.0.dist-info/WHEEL
CBZpliers-0.2.0.dist-info/entry_points.txt
CBZpliers-0.2.0.dist-info/top_level.txt
CBZpliers-0.2.0.dist-info/RECORD
