Metadata-Version: 2.1
Name: CBZpliers
Version: 0.2.0
Summary: A tool to combine multiple .cbz files into one.
Home-page: https://github.com/Sigosu/CBZpliers
Author: Szymon Sciegienka
Author-email: szymon.sciegienka@gmail.com
Classifier: Programming Language :: Python :: 3
Classifier: License :: OSI Approved :: MIT License
Classifier: Operating System :: OS Independent
Requires-Python: >=3.6
License-File: LICENSE
Requires-Dist: lxml
